waterfall_custom_plot/__init__.py
waterfall_custom_plot/example.py
waterfall_custom_plot/frontend/build/asset-manifest.json
waterfall_custom_plot/frontend/build/bootstrap.min.css
waterfall_custom_plot/frontend/build/bootstrap.min.css.map
waterfall_custom_plot/frontend/build/index.html
waterfall_custom_plot/frontend/build/static/css/main.22c72976.css
waterfall_custom_plot/frontend/build/static/css/main.22c72976.css.map
waterfall_custom_plot/frontend/build/static/js/main.bbd83478.js
waterfall_custom_plot/frontend/build/static/js/main.bbd83478.js.LICENSE.txt
waterfall_custom_plot/frontend/build/static/js/main.bbd83478.js.map
waterfall_custom_plot-0.0.1.dist-info/LICENSE
waterfall_custom_plot-0.0.1.dist-info/METADATA
waterfall_custom_plot-0.0.1.dist-info/WHEEL
waterfall_custom_plot-0.0.1.dist-info/top_level.txt
waterfall_custom_plot-0.0.1.dist-info/RECORD
